pastes/__init__.py
pastes/main.py
pastes-1.5.1.dist-info/licenses/LICENSE
pastes-1.5.1.dist-info/METADATA
pastes-1.5.1.dist-info/WHEEL
pastes-1.5.1.dist-info/top_level.txt
pastes-1.5.1.dist-info/RECORD
