Metadata-Version: 2.4
Name: pastes
Version: 1.5.1
Summary: Minimalistic Python client for pastes.dev
Author-email: RimMirK <me@RimMirK.pp.ua>
Project-URL: Repository, https://github.com/RimMirK/pastes
Keywords: paste,pastes,pastes.dev,code,pastebin,client,share,send
Classifier: Development Status :: 5 - Production/Stable
Classifier: Intended Audience :: Developers
Classifier: Topic :: Software Development :: Libraries
Classifier: License :: OSI Approved :: GNU General Public License v3 (GPLv3)
Classifier: Programming Language :: Python :: 3
Classifier: Programming Language :: Python :: 3.8
Classifier: Programming Language :: Python :: 3.9
Classifier: Programming Language :: Python :: 3.10
Classifier: Programming Language :: Python :: 3.11
Classifier: Programming Language :: Python :: 3.12
Classifier: Operating System :: OS Independent
Requires-Python: >=3.8
License-File: LICENSE
Requires-Dist: requests
Requires-Dist: httpx
Dynamic: license-file
